Autostart_app/autostart_create.py
Autostart_app-1.0.0.4.dist-info/LICENSE
Autostart_app-1.0.0.4.dist-info/METADATA
Autostart_app-1.0.0.4.dist-info/WHEEL
Autostart_app-1.0.0.4.dist-info/entry_points.txt
Autostart_app-1.0.0.4.dist-info/top_level.txt
Autostart_app-1.0.0.4.dist-info/RECORD
