Metadata-Version: 2.1
Name: Autostart-app
Version: 1.0.0.4
Summary: A Python package to autostart your desktop application when your system turn-on
Home-page: https://github.com/Vijayraj72/Autostart-app
Author: vijay saw
Author-email: imvijayraj72@gmail.com
License: MIT
Platform: UNKNOWN
Classifier: License :: OSI Approved :: MIT License
Classifier: Programming Language :: Python :: 3
Classifier: Programming Language :: Python :: 3.7
